pipeasy_spark/__init__.py
pipeasy_spark/convenience.py
pipeasy_spark/core.py
pipeasy_spark/transformers.py
pipeasy_spark-0.2.1.dist-info/LICENSE
pipeasy_spark-0.2.1.dist-info/METADATA
pipeasy_spark-0.2.1.dist-info/WHEEL
pipeasy_spark-0.2.1.dist-info/top_level.txt
pipeasy_spark-0.2.1.dist-info/RECORD
