Metadata-Version: 2.1
Name: pipeasy-spark
Version: 0.2.1
Summary: an easy way to define preprocessing data pipelines for pysparark
Home-page: https://github.com/BenjaminHabert/pipeasy_spark
Author: Benjamin Habert
Author-email: bhabert@quantmetry.com
License: MIT license
Keywords: pipeasy_spark
Platform: UNKNOWN
Classifier: Development Status :: 2 - Pre-Alpha
Classifier: Intended Audience :: Developers
Classifier: License :: OSI Approved :: MIT License
Classifier: Natural Language :: English
Classifier: Programming Language :: Python :: 2
Classifier: Programming Language :: Python :: 2.7
Classifier: Programming Language :: Python :: 3
Classifier: Programming Language :: Python :: 3.4
Classifier: Programming Language :: Python :: 3.5
Classifier: Programming Language :: Python :: 3.6
Classifier: Programming Language :: Python :: 3.7
Requires-Dist: pyspark
Requires-Dist: numpy
